dcifr_package/__init__.py
dcifr_package/dcifr.py
dcifr-0.0.1.dist-info/LICENSE.txt
dcifr-0.0.1.dist-info/METADATA
dcifr-0.0.1.dist-info/WHEEL
dcifr-0.0.1.dist-info/top_level.txt
dcifr-0.0.1.dist-info/RECORD
