Metadata-Version: 2.1
Name: dcifr
Version: 0.0.1
Summary: DCiFR (Demographic Characteristics in Facial Recognition) is a wrapper software that allows you to run deep learning models to parse demographic characteristics from an image.
Home-page: https://github.com/mlraglin/DCiFR
Author: Melina Raglin
Author-email: raglin.11@buckeyemail.osu.edu
License: UNKNOWN
Project-URL: Bug Tracker, https://github.com/mlraglin/DCiFR/issues
Platform: UNKNOWN
Classifier: Programming Language :: Python :: 3
Classifier: License :: OSI Approved :: GNU Affero General Public License v3 or later (AGPLv3+)
Classifier: Operating System :: OS Independent
Requires-Python: >=3.6
License-File: LICENSE.txt
